AngularjsRumenjiaocheng/README.md
AngularjsRumenjiaocheng/__init__.py
AngularjsRumenjiaocheng/__main__.py
AngularjsRumenjiaocheng/file.epub
AngularjsRumenjiaocheng/index.html
AngularjsRumenjiaocheng/css/__init__.py
AngularjsRumenjiaocheng/css/annotations.css
AngularjsRumenjiaocheng/css/main.css
AngularjsRumenjiaocheng/css/normalize.css
AngularjsRumenjiaocheng/css/popup.css
AngularjsRumenjiaocheng/font/__init__.py
AngularjsRumenjiaocheng/font/fontello.eot
AngularjsRumenjiaocheng/font/fontello.svg
AngularjsRumenjiaocheng/font/fontello.ttf
AngularjsRumenjiaocheng/font/fontello.woff
AngularjsRumenjiaocheng/img/__init__.py
AngularjsRumenjiaocheng/img/annotator-glyph-sprite.png
AngularjsRumenjiaocheng/img/annotator-icon-sprite.png
AngularjsRumenjiaocheng/img/apple-touch-icon.png
AngularjsRumenjiaocheng/img/cancelfullscreen.png
AngularjsRumenjiaocheng/img/close.png
AngularjsRumenjiaocheng/img/fullscreen.png
AngularjsRumenjiaocheng/img/loader.gif
AngularjsRumenjiaocheng/img/menu-icon.png
AngularjsRumenjiaocheng/img/save.png
AngularjsRumenjiaocheng/img/saved.png
AngularjsRumenjiaocheng/img/settings-s.png
AngularjsRumenjiaocheng/img/settings.png
AngularjsRumenjiaocheng/img/star.png
AngularjsRumenjiaocheng/js/__init__.py
AngularjsRumenjiaocheng/js/epub.js
AngularjsRumenjiaocheng/js/epub.min.js
AngularjsRumenjiaocheng/js/epub.min.map
AngularjsRumenjiaocheng/js/hooks.min.js
AngularjsRumenjiaocheng/js/hooks.min.map
AngularjsRumenjiaocheng/js/reader.js
AngularjsRumenjiaocheng/js/reader.js.map
AngularjsRumenjiaocheng/js/reader.min.js
AngularjsRumenjiaocheng/js/reader.min.map
AngularjsRumenjiaocheng/js/hooks/__init__.py
AngularjsRumenjiaocheng/js/hooks/extensions/__init__.py
AngularjsRumenjiaocheng/js/hooks/extensions/highlight.js
AngularjsRumenjiaocheng/js/libs/__init__.py
AngularjsRumenjiaocheng/js/libs/jquery.min.js
AngularjsRumenjiaocheng/js/libs/localforage.min.js
AngularjsRumenjiaocheng/js/libs/screenfull.js
AngularjsRumenjiaocheng/js/libs/screenfull.min.js
angularjs_rumenjiaocheng-2024.2.29.0.dist-info/METADATA
angularjs_rumenjiaocheng-2024.2.29.0.dist-info/WHEEL
angularjs_rumenjiaocheng-2024.2.29.0.dist-info/entry_points.txt
angularjs_rumenjiaocheng-2024.2.29.0.dist-info/top_level.txt
angularjs_rumenjiaocheng-2024.2.29.0.dist-info/RECORD
